easy_pdf/__init__.py
easy_pdf/apps.py
easy_pdf/exceptions.py
easy_pdf/models.py
easy_pdf/rendering.py
easy_pdf/tests.py
easy_pdf/utils.py
easy_pdf/views.py
easy_pdf/templates/easy_pdf/base.html
dj_easy_pdf-0.4.7.dist-info/LICENSE
dj_easy_pdf-0.4.7.dist-info/METADATA
dj_easy_pdf-0.4.7.dist-info/WHEEL
dj_easy_pdf-0.4.7.dist-info/top_level.txt
dj_easy_pdf-0.4.7.dist-info/RECORD
