Metadata-Version: 2.1
Name: dj-easy-pdf
Version: 0.4.7
Summary: Django PDF views, easily convert html responses to pdf responses
Home-page: https://github.com/WilliamOtieno/dj-easy-pdf
Author: William Otieno
Author-email: jimmywilliamotieno@gmail.com
License: MIT
Keywords: dj-easy-pdf
Classifier: Development Status :: 5 - Production/Stable
Classifier: Environment :: Web Environment
Classifier: Framework :: Django
Classifier: Intended Audience :: Developers
Classifier: License :: OSI Approved :: MIT License
Classifier: Operating System :: OS Independent
Classifier: Natural Language :: English
Classifier: Programming Language :: Python :: 3.7
Classifier: Programming Language :: Python :: 3.8
Classifier: Programming Language :: Python :: 3.9
Classifier: Programming Language :: Python :: 3.10
Classifier: Programming Language :: Python :: 3.11
Classifier: Topic :: Software Development :: Libraries :: Python Modules
License-File: LICENSE
Requires-Dist: django (>=3.2)
Requires-Dist: xhtml2pdf (>=0.2)
Requires-Dist: reportlab (>=3)
Requires-Dist: requests
